<Properties StartupConfiguration="{DAD0E433-2611-C1F7-9136-C7B69DCB77AD}|">
  <MonoDevelop.Ide.Workbench ActiveDocument="Assets/Scripts/DestroyOverLiftime.cs">
    <Files>
      <File FileName="Assets/Scripts/BattleManager.cs" Line="223" Column="4" />
      <File FileName="Assets/Scripts/GameManager.cs" Line="36" Column="1" />
      <File FileName="Assets/Scripts/AreaEntrance.cs" Line="16" Column="1" />
      <File FileName="Assets/Scripts/AreaController.cs" Line="16" Column="1" />
      <File FileName="Assets/Scripts/EssentialsLoader.cs" Line="36" Column="6" />
      <File FileName="Assets/Scripts/CameraConroller.cs" Line="36" Column="1" />
      <File FileName="Assets/Scripts/PlayerController.cs" Line="15" Column="32" />
      <File FileName="Assets/Scripts/UIFade.cs" Line="22" Column="1" />
      <File FileName="Assets/Scripts/DialogManager.cs" Line="31" Column="1" />
      <File FileName="Assets/Scripts/GameMenu.cs" Line="61" Column="1" />
      <File FileName="Assets/Scripts/QuestManager.cs" Line="21" Column="1" />
      <File FileName="Assets/Scripts/CharStats.cs" Line="48" Column="1" />
      <File FileName="Assets/Scripts/BattleCharacter.cs" Line="22" Column="22" />
      <File FileName="Assets/Scripts/AttackEffect.cs" Line="16" Column="37" />
      <File FileName="Assets/Scripts/BattleMove.cs" Line="3" Column="22" />
      <File FileName="Assets/Scripts/DestroyOverLiftime.cs" Line="16" Column="6" />
    </Files>
  </MonoDevelop.Ide.Workbench>
  <MonoDevelop.Ide.DebuggingService.PinnedWatches />
  <MonoDevelop.Ide.Workspace ActiveConfiguration="Debug" />
  <MonoDevelop.Ide.ItemProperties.Assembly-CSharp PreferredExecutionTarget="Unity.Editor" />
  <MonoDevelop.Ide.DebuggingService.Breakpoints>
    <BreakpointStore>
      <Breakpoint file="/Users/Alexander/MyFirstRPG/Assets/Scripts/CharStats.cs" relfile="Assets/Scripts/CharStats.cs" line="86" column="15" />
      <Breakpoint file="/Users/Alexander/MyFirstRPG/Assets/Scripts/CharStats.cs" relfile="Assets/Scripts/CharStats.cs" line="61" column="1" />
      <Breakpoint file="/Users/Alexander/MyFirstRPG/Assets/Scripts/ShopKeeper.cs" relfile="Assets/Scripts/ShopKeeper.cs" line="17" column="1" />
      <Breakpoint file="/Users/Alexander/MyFirstRPG/Assets/Scripts/AreaEntrance.cs" relfile="Assets/Scripts/AreaEntrance.cs" line="16" column="1" />
      <Breakpoint file="/Users/Alexander/MyFirstRPG/Assets/Scripts/EssentialsLoader.cs" relfile="Assets/Scripts/EssentialsLoader.cs" line="12" column="1" />
    </BreakpointStore>
  </MonoDevelop.Ide.DebuggingService.Breakpoints>
  <MultiItemStartupConfigurations />
</Properties>